LICENSE.txt
README.md
setup.py
risk_model_maidou/__init__.py
risk_model_maidou/build_model.py
risk_model_maidou/fenbin.py
risk_model_maidou/model_train.py
risk_model_maidou.egg-info/PKG-INFO
risk_model_maidou.egg-info/SOURCES.txt
risk_model_maidou.egg-info/dependency_links.txt
risk_model_maidou.egg-info/top_level.txt